pycec/__init__.py
pycec/__main__.py
pycec/cec.py
pycec/commands.py
pycec/const.py
pycec/network.py
pycec/tcp.py
pyCEC-0.5.1.dist-info/LICENSE
pyCEC-0.5.1.dist-info/METADATA
pyCEC-0.5.1.dist-info/WHEEL
pyCEC-0.5.1.dist-info/entry_points.txt
pyCEC-0.5.1.dist-info/top_level.txt
pyCEC-0.5.1.dist-info/RECORD
